cvae/__init__.py
cvae/cvae.py
cvae/lib/__init__.py
cvae/lib/data_reader.py
cvae/lib/data_reader_array.py
cvae/lib/functions.py
cvae/lib/model_iaf.py
cvae-0.2.0.dist-info/LICENSE.txt
cvae-0.2.0.dist-info/METADATA
cvae-0.2.0.dist-info/WHEEL
cvae-0.2.0.dist-info/top_level.txt
cvae-0.2.0.dist-info/RECORD
