Metadata-Version: 2.2
Name: cvae
Version: 0.2.0
Summary: CompressionVAE: General purpose dimensionality reduction and manifold learning tool based on Variational Autoencoder.
Home-page: https://github.com/maxfrenzel/CompressionVAE
Author: Max Frenzel
Author-email: maxfrenzel+cvae@gmail.com
Keywords: vae variational autoencoder manifold dimensionality reduction compression tensorflow
Classifier: Programming Language :: Python :: 3
Classifier: License :: OSI Approved :: MIT License
Classifier: Operating System :: OS Independent
Requires-Python: >=3.6
License-File: LICENSE.txt
Requires-Dist: numpy<1.23.0,>=1.16.5
Requires-Dist: matplotlib<4.0.0,>=3.3.0
Requires-Dist: joblib<2.0.0,>=1.0.0
Requires-Dist: tqdm<5.0.0,>=4.50.0
Requires-Dist: pandas<2.0.0,>=1.3.0
Requires-Dist: tensorflow-macos==2.8.0
Requires-Dist: tensorflow-metal==0.4.0
Provides-Extra: test
Requires-Dist: scikit-learn>=1.0.0; extra == "test"
Dynamic: author
Dynamic: author-email
Dynamic: classifier
Dynamic: description
Dynamic: description-content-type
Dynamic: home-page
Dynamic: keywords
Dynamic: provides-extra
Dynamic: requires-dist
Dynamic: requires-python
Dynamic: summary
